{"changelog":[{"ChangeList":[{"Id":"fba98dc8-70f6-11eb-98b1-644a43c1ec54","ApiChange":"Resource","ChangedApiName":"reportRoot","ChangeType":"Addition","Description":"Added the [reportRoot](https://docs.microsoft.com/en-us/graph/api/resources/reportRoot?view=graph-rest-beta) resource type.","Target":"reportRoot"},{"Id":"fbac54ce-70f6-11eb-98b1-644a43c1ec54","ApiChange":"Resource","ChangedApiName":"report","ChangeType":"Addition","Description":"Added the [report](https://docs.microsoft.com/en-us/graph/api/resources/report?view=graph-rest-beta) resource type.","Target":"report"},{"Id":"fbb0bdc3-70f6-11eb-98b1-644a43c1ec54","ApiChange":"Method","ChangedApiName":"getTenantSecureScores","ChangeType":"Addition","Description":"Added the [getTenantSecureScores](https://docs.microsoft.com/en-us/graph/api/reportRoot-getTenantSecureScores?view=graph-rest-beta) method to the [reportRoot](https://docs.microsoft.com/en-us/graph/api/resources/reportRoot?view=graph-rest-beta) resource.","Target":"reportRoot"}],"Id":"fba6e335-70f6-11eb-98b1-644a43c1ec54","Cloud":"prd","Version":"beta","CreatedDateTime":"2021-02-17T08:06:05.121Z","WorkloadArea":"Security","SubArea":""}]}