{"changelog":[{"ChangeList":[{"Id":"46aa07ad-99af-11eb-8cb0-33bc249d550e","ApiChange":"Resource","ChangedApiName":"Json","ChangeType":"Addition","Description":"Added the [Json](https://docs.microsoft.com/en-us/graph/api/resources/Json?view=graph-rest-beta) resource type.","Target":"Json"},{"Id":"46ac6a7c-99af-11eb-8cb0-33bc249d550e","ApiChange":"Member","ChangedApiName":"iconUrl","ChangeType":"Addition","Description":"Added the `iconUrl` member to the **label** enumeration.","Target":"label"},{"Id":"46aecb45-99af-11eb-8cb0-33bc249d550e","ApiChange":"Member","ChangedApiName":"containerName","ChangeType":"Addition","Description":"Added the `containerName` member to the **label** enumeration.","Target":"label"},{"Id":"46b12f55-99af-11eb-8cb0-33bc249d550e","ApiChange":"Member","ChangedApiName":"containerUrl","ChangeType":"Addition","Description":"Added the `containerUrl` member to the **label** enumeration.","Target":"label"}],"Id":"46a7a54f-99af-11eb-8cb0-33bc249d550e","Cloud":"prd","Version":"beta","CreatedDateTime":"2021-04-10T03:46:04.865Z","WorkloadArea":"","SubArea":""}]}